stampdb/__init__.py
stampdb/point.py
stampdb/schema.py
stampdb/stampdb.py
stampdb/_backend/__init__.py
stampdb/_backend/_types.cpython-313-aarch64-linux-gnu.so
stampdb/relational/__init__.py
stampdb/relational/joins.py
stampdb/relational/simple.py
stampdb-1.0.0.dist-info/METADATA
stampdb-1.0.0.dist-info/WHEEL
stampdb-1.0.0.dist-info/top_level.txt
stampdb-1.0.0.dist-info/RECORD
stampdb-1.0.0.dist-info/licenses/LICENSE
