Metadata-Version: 2.4
Name: stampdb
Version: 1.0.0
Summary: A tiny C++ Time Series Database library designed for compatibility with the PyData Ecosystem.
Home-page: https://github.com/aadya940/stampdb
Author: Aadya A. Chinubhai
Author-email: aadyachinubhai@gmail.com
Classifier: Development Status :: 3 - Alpha
Classifier: Intended Audience :: Developers
Classifier: Programming Language :: Python :: 3
Classifier: Programming Language :: C++
Requires-Python: >=3.7
License-File: LICENSE
Requires-Dist: numpy
Requires-Dist: pybind11
Requires-Dist: setuptools
Requires-Dist: wheel
Requires-Dist: build
Dynamic: author
Dynamic: author-email
Dynamic: classifier
Dynamic: description
Dynamic: description-content-type
Dynamic: home-page
Dynamic: license-file
Dynamic: requires-dist
Dynamic: requires-python
Dynamic: summary
